WedgieIntegrator/__init__.py
WedgieIntegrator/asyncio_workaround.py
WedgieIntegrator/auth.py
WedgieIntegrator/client.py
WedgieIntegrator/exceptions.py
WedgieIntegrator/response.py
WedgieIntegrator/utils.py
WedgieIntegrator-0.1.5.0.dist-info/LICENSE
WedgieIntegrator-0.1.5.0.dist-info/METADATA
WedgieIntegrator-0.1.5.0.dist-info/WHEEL
WedgieIntegrator-0.1.5.0.dist-info/top_level.txt
WedgieIntegrator-0.1.5.0.dist-info/RECORD
