Metadata-Version: 2.1
Name: WedgieIntegrator
Version: 0.1.5.0
Summary: An API client toolkit that is async friendly
Home-page: https://github.com/deathbywedgie/WedgieIntegrator
Author: Chad Roberts
Author-email: jcbroberts@gmail.com
Classifier: Programming Language :: Python :: 3
Classifier: License :: OSI Approved :: MIT License
Classifier: Operating System :: OS Independent
Requires-Python: >=3.7
License-File: LICENSE
Requires-Dist: httpx
Requires-Dist: pydantic
Requires-Dist: tenacity
Requires-Dist: structlog
